repo_review/__init__.py
repo_review/__main__.py
repo_review/_version.py
repo_review/_version.pyi
repo_review/checks.py
repo_review/families.py
repo_review/fixtures.py
repo_review/ghpath.py
repo_review/html.py
repo_review/processor.py
repo_review/py.typed
repo_review/schema.py
repo_review/testing.py
repo_review/_compat/__init__.py
repo_review/_compat/tomllib.py
repo_review/_compat/typing.py
repo_review/_compat/importlib/__init__.py
repo_review/_compat/importlib/resources/__init__.py
repo_review/_compat/importlib/resources/abc.py
repo_review/resources/__init__.py
repo_review/resources/repo-review.schema.json
repo_review-0.12.3.dist-info/METADATA
repo_review-0.12.3.dist-info/WHEEL
repo_review-0.12.3.dist-info/entry_points.txt
repo_review-0.12.3.dist-info/licenses/LICENSE
repo_review-0.12.3.dist-info/RECORD
