Metadata-Version: 2.4
Name: repo_review
Version: 0.12.3
Summary: Framework that can run checks on repos
Project-URL: Changelog, https://github.com/scientific-python/repo-review/releases
Project-URL: Demo, https://scientific-python.github.io/repo-review
Project-URL: Documentation, https://repo-review.readthedocs.io
Project-URL: Homepage, https://repo-review.readthedocs.io
Project-URL: Source, https://github.com/scientific-python/repo-review
Author-email: Henry Schreiner <henryfs@princeton.edu>
License-File: LICENSE
Classifier: Development Status :: 4 - Beta
Classifier: Environment :: Console
Classifier: Environment :: WebAssembly :: Emscripten
Classifier: Intended Audience :: Developers
Classifier: Intended Audience :: Science/Research
Classifier: License :: OSI Approved :: BSD License
Classifier: Operating System :: OS Independent
Classifier: Programming Language :: Python
Classifier: Programming Language :: Python :: 3
Classifier: Programming Language :: Python :: 3.10
Classifier: Programming Language :: Python :: 3.11
Classifier: Programming Language :: Python :: 3.12
Classifier: Programming Language :: Python :: 3.13
Classifier: Programming Language :: Python :: 3.14
Classifier: Topic :: Software Development :: Libraries :: Python Modules
Classifier: Topic :: Software Development :: Quality Assurance
Classifier: Typing :: Typed
Requires-Python: >=3.10
Requires-Dist: markdown-it-py
Requires-Dist: pyyaml
Requires-Dist: tomli; python_version < '3.11'
Requires-Dist: typing-extensions; python_version < '3.11'
Provides-Extra: cli
Requires-Dist: click>=8; extra == 'cli'
Requires-Dist: rich-click; extra == 'cli'
Requires-Dist: rich>=12.2; extra == 'cli'
